meo/__init__.py
meo/__version__.py
meo/flask.py
meo/io.py
meo/net.py
meo/screen.py
meo/thread.py
meo/utils.py
meo/wapper.py
meo/crack/__init__.py
meo/crack/cracker.py
meo/crack/pdf.py
meo/crack/utils.py
meo/crack/zip.py
meo-0.1.13.dist-info/LICENSE
meo-0.1.13.dist-info/METADATA
meo-0.1.13.dist-info/WHEEL
meo-0.1.13.dist-info/top_level.txt
meo-0.1.13.dist-info/RECORD
