Metadata-Version: 2.1
Name: meo
Version: 0.1.13
Summary: frequently-used function library
Home-page: http://github.com/miaobuao/meo
Author: miaobuao
Author-email: miaobuao@outlook.com
License: MIT License
Classifier: Programming Language :: Python :: 3
Classifier: License :: OSI Approved :: Apache Software License
Classifier: Operating System :: OS Independent
License-File: LICENSE
Requires-Dist: json5 (>=0.9)
